vcsi/VERSION
vcsi/__init__.py
vcsi/vcsi.py
vcsi-7.0.15.dist-info/entry_points.txt
vcsi-7.0.15.dist-info/LICENSE
vcsi-7.0.15.dist-info/WHEEL
vcsi-7.0.15.dist-info/METADATA
vcsi-7.0.15.dist-info/RECORD
