Metadata-Version: 2.1
Name: vcsi
Version: 7.0.15
Summary: Create video contact sheets, thumbnails, screenshots
License: MIT
Author: Nils Amiet
Author-email: amietn@foobar.tld
Requires-Python: >=3.8,<4.0
Classifier: License :: OSI Approved :: MIT License
Classifier: Programming Language :: Python :: 3
Classifier: Programming Language :: Python :: 3.8
Classifier: Programming Language :: Python :: 3.9
Classifier: Programming Language :: Python :: 3.10
Classifier: Programming Language :: Python :: 3.11
Requires-Dist: jinja2 (>=3.1.2,<4.0.0)
Requires-Dist: numpy (>=1.24.3,<2.0.0)
Requires-Dist: parsedatetime (>=2.6,<3.0)
Requires-Dist: pillow (>=9.5.0,<10.0.0)
Requires-Dist: texttable (>=1.6.7,<2.0.0)
